{
"users":[
{
"username":"gopi",
"password":"penfish336",
"contacts":[
{
"username":"komanduri",
"username":"Testuser2",
"username":"Testuser5"
}
]
},
{
"username":"krishna"
"password":"bananatable143",
"contacts":[
{
"username":"komanduri",
"username":"Testuser1",
"username":"Testuser2"
}
]
},
{
"username":"komanduri"
"password":"welcome12!",
"contacts":[
{
"username":"krishna",
"username":"Testuser1",
"username":"Testuser2"
"username":"Testuser3"
}
]
},
{
"username":"TestUser1"
"password":"Testuser1",
"contacts":[
{
"username":"gopi",
"username":"Testuser2",
"username":"Testuser3"
}
]
},
{
"username":"TestUser2"
"password":"Testuser2",
"contacts":[
{
"username":"komanduri",
"username":"Testuser2",
"username":"Testuser5"
}
]
},
{
"username":"TestUser3"
"password":"Testuser3",
"contacts":[
{
"username":"komanduri",
"username":"Testuser2",
"username":"Testuser5"
}
]
},
{
"username":"TestUser4"
"password":"Testuser4",
"contacts":[
{
"username":"gopi",
"username":"Testuser4",
"username":"Testuser5"
}
]
},
{
"username":"TestUser5"
"password":"Testuser5",
"contacts":[
{
"username":"Testuser4",
"username":"Testuser2",
"username":"Testuser3"
}
]
},
{
"username":"TestUser6"
"password":"Testuser6",
"contacts":[
{
"username":"gopi",
"username":"krishna",
"username":"komanduri"
}
]
},
{
"username":"TestUser7"
"password":"Testuser7",
"contacts":[
{
"username":"komanduri",
"username":"Testuser1",
"username":"Testuser3"
}
]
},
{
"username":"TestUser8"
"password":"Testuser8",
"contacts":[
{
"username":"komanduri",
"username":"Testuser8",
"username":"Testuser1",
"username":"komanduri",
"username":"gopi"
}
]
},
{
"username":"TestUser9"
"password":"Testuser9",
"contacts":[
{
"username":"komanduri",
"username":"Testuser4",
"username":"Testuser5"
}
]
},
{
"username":"TestUser10"
"password":"Testuser10",
"contacts":[
{
"username":"komanduri",
"username":"Testuser2",
"username":"Testuser7"
}
]
}
]
}